Workbook

Sheet Comece Aqui
A1: 📌 ORÇAMENTO DE OBRA — COMO USAR ESTA PLANILHA
A2: 📌 Início | B2: 📊 Dashboard | C2: 📁 Projeto | D2: 🧱 Materiais | E2: 👷 Mão de Obra | F2: 💰 Custos Adic. | G2: 📈 Resumo | H2: 📄 Condições
B4: 1️⃣ Dados do Projeto
B5: Preencha o nome do projeto, cliente, localização e datas na aba "Projeto".
B7: 2️⃣ Materiais e Mão de Obra
B8: Insira quantidades e preços nas abas "Materiais" e "Mão de Obra" — os subtotais são calculados automaticamente.
B10: 3️⃣ Margem / BDI
B11: Na aba "Resumo", escolha se a margem incide sobre o Total ou só sobre a Mão de Obra, e defina a percentagem.
B13: 4️⃣ Dashboard e Impressão
B14: Veja o resumo final no "Dashboard" e use Ctrl+P para exportar em PDF (já configurado para caber numa página).
B16: LEGENDA DE CORES
C17: Célula amarela = preencher manualmente
C18: Vermelho = dado obrigatório em falta / alerta de custo elevado
C19: Amarelo forte = linha com informação incompleta

Sheet Dashboard
A1: ORÇAMENTO DE OBRA - DASHBOARD
A2: 📌 Início | B2: 📊 Dashboard | C2: 📁 Projeto | D2: 🧱 Materiais | E2: 👷 Mão de Obra | F2: 💰 Custos Adic. | G2: 📈 Resumo | H2: 📄 Condições
A3: PROJETO
A4: Nome Projeto: | B4: =Projeto!B3 -> 0
A5: Cliente: | B5: =Projeto!B4 -> 0
A6: Localização: | B6: =Projeto!B5 -> 0
A7: Data Orçamento: | B7: =Projeto!B6 -> 25/06/2026
A8: Engenheiro: | B8: =Projeto!B7 -> 0
A10: RESUMO FINANCEIRO
A11: Subtotal Materiais: | B11: =Materiais!F35 -> 0
A12: Subtotal Mão Obra: | B12: =MaoObra!F25 -> 8221
A13: Subtotal Custos Adic: | B13: =CustosAdicionais!E15 -> 0
A14: Subtotal ANTES de Margem: | B14: =Resume!B7 -> 8221
A15: % Margem Lucro: | B15: =Resume!B9 -> 25
A16: Valor Margem: | B16: =Resume!B10 -> 2055.25
A17: TOTAL ORÇAMENTO: | B17: =Resume!B11 -> 10276.25

Sheet Projeto
A1: DADOS DO PROJETO
A2: 📌 Início | B2: 📊 Dashboard | C2: 📁 Projeto | D2: 🧱 Materiais | E2: 👷 Mão de Obra | F2: 💰 Custos Adic. | G2: 📈 Resumo | H2: 📄 Condições
A3: Nome Projeto
A4: Cliente
A5: Localização
A6: Data Orçamento | B6: 25/06/2026
A7: Engenheiro/Responsável
A8: Telefone Cliente
A9: Email Cliente
A10: Data Início Previsto
A11: Data Conclusão Prevista
A12: Descrição Projeto

Sheet Materiais
A1: MATERIAIS DE CONSTRUÇÃO
A2: 📌 Início | B2: 📊 Dashboard | C2: 📁 Projeto | D2: 🧱 Materiais | E2: 👷 Mão de Obra | F2: 💰 Custos Adic. | G2: 📈 Resumo | H2: 📄 Condições
A3: Categoria | B3: Material | C3: Unidade | D3: Quantidade | E3: Preço Unit (Kz) | F3: Subtotal (Kz) | G3: Observação
A4: ESTRUTURA
F5: =D5*E5 -> 0
F6: =D6*E6 -> 0
F7: =D7*E7 -> 0
F8: =D8*E8 -> 0
F9: =D9*E9 -> 0
A10: ALVENARIA
F11: =D11*E11 -> 0
F12: =D12*E12 -> 0
F13: =D13*E13 -> 0
F14: =D14*E14 -> 0
F15: =D15*E15 -> 0
A16: REVESTIMENTO
F17: =D17*E17 -> 0
F18: =D18*E18 -> 0
F19: =D19*E19 -> 0
F20: =D20*E20 -> 0
F21: =D21*E21 -> 0
A22: COBERTA
F23: =D23*E23 -> 0
F24: =D24*E24 -> 0
F25: =D25*E25 -> 0
F26: =D26*E26 -> 0
F27: =D27*E27 -> 0
A28: ACABAMENTO
F29: =D29*E29 -> 0
F30: =D30*E30 -> 0
F31: =D31*E31 -> 0
F32: =D32*E32 -> 0
F33: =D33*E33 -> 0
A35: TOTAL MATERIAIS | F35: =SUM(F4:F33) -> 0

Sheet MaoObra
A1: MÃO DE OBRA
A2: 📌 Início | B2: 📊 Dashboard | C2: 📁 Projeto | D2: 🧱 Materiais | E2: 👷 Mão de Obra | F2: 💰 Custos Adic. | G2: 📈 Resumo | H2: 📄 Condições
A3: Categoria | B3: Profissão | C3: Quantidade | D3: Dias Trabalho | E3: Custo Diário (Kz) | F3: Subtotal (Kz) | G3: Observação
A4: ESTRUTURA
F5: =C5*D5*E5 -> 0
F6: =C6*D6*E6 -> 0
F7: 444
F8: =C8*D8*E8 -> 0
A9: ALVENARIA
F10: =C10*D10*E10 -> 0
F11: =C11*D11*E11 -> 0
F12: 7777
F13: =C13*D13*E13 -> 0
A14: REVESTIMENTO
F15: =C15*D15*E15 -> 0
F16: =C16*D16*E16 -> 0
F17: =C17*D17*E17 -> 0
F18: =C18*D18*E18 -> 0
A19: ACABAMENTO
F20: =C20*D20*E20 -> 0
F21: =C21*D21*E21 -> 0
F22: =C22*D22*E22 -> 0
F23: =C23*D23*E23 -> 0
A25: TOTAL MÃO DE OBRA | F25: =SUM(F4:F23) -> 8221

Sheet CustosAdicionais
A1: CUSTOS ADICIONAIS
A2: 📌 Início | B2: 📊 Dashboard | C2: 📁 Projeto | D2: 🧱 Materiais | E2: 👷 Mão de Obra | F2: 💰 Custos Adic. | G2: 📈 Resumo | H2: 📄 Condições
A3: Descrição | B3: Quantidade | C3: Unidade | D3: Valor (Kz) | E3: Subtotal (Kz) | F3: Observação
E4: =B4*D4 -> 0
E5: =B5*D5 -> 0
E6: =B6*D6 -> 0
E7: =B7*D7 -> 0
E8: =B8*D8 -> 0
E9: =B9*D9 -> 0
E10: =B10*D10 -> 0
E11: =B11*D11 -> 0
E12: =B12*D12 -> 0
E13: =B13*D13 -> 0
A15: TOTAL CUSTOS ADICIONAIS | E15: =SUM(E4:E13) -> 0

Sheet Resume
A1: RESUMO ORÇAMENTÁRIO
A2: 📌 Início | B2: 📊 Dashboard | C2: 📁 Projeto | D2: 🧱 Materiais | E2: 👷 Mão de Obra | F2: 💰 Custos Adic. | G2: 📈 Resumo | H2: 📄 Condições
A3: Materiais | B3: =Materiais!F35 -> 0
A4: Mão de Obra | B4: =MaoObra!F25 -> 8221
A5: Custos Adicionais | B5: =CustosAdicionais!E15 -> 0
A7: SUBTOTAL | B7: =B3+B4+B5 -> 8221
A8: Base Cálculo Margem/BDI | B8: Total
A9: MARGEM EMPRESA (%) | B9: 25
A10: VALOR MARGEM | B10: =IF(B8="Total",B7,B4)*B9/100 -> 2055.25
A11: PREÇO FINAL (COM MARGEM) | B11: =B7+B10 -> 10276.25

Sheet Condicoes
A1: TERMOS E CONDIÇÕES
A2: 📌 Início | B2: 📊 Dashboard | C2: 📁 Projeto | D2: 🧱 Materiais | E2: 👷 Mão de Obra | F2: 💰 Custos Adic. | G2: 📈 Resumo | H2: 📄 Condições
A3: Validade Orçamento: | B3: 30 dias
A4: Prazo Pagamento: | B4: Entrada 50% | Saldo Conclusão
A5: Forma Pagamento: | B5: Transferência Bancária / Dinheiro
A6: Prazinho Execução:
A7: Observações Especiais:
A8: Responsável Assinatura:
A9: Data Assinatura:
